matrixreg/__init__.py
matrixreg/matrixregression.py
matrixreg/online_vectorizers.py
matrixreg-0.3.0.dist-info/licenses/LICENSE
matrixreg-0.3.0.dist-info/WHEEL
matrixreg-0.3.0.dist-info/METADATA
matrixreg-0.3.0.dist-info/RECORD
