Metadata-Version: 2.4
Name: matrixreg
Version: 0.3.0
Summary: Implementation of the MatrixRegression (MR) algorithm for online-learning multi-label text classification, by Popa, Zeitouni & Gardarin.
Keywords: text-classification,multi-label-classification,online-learning
Author-email: Nicolò Verardo <n.verardo@outlook.com>
Requires-Python: >=3.10,<3.15
Classifier: Development Status :: 4 - Beta
Classifier: Intended Audience :: Developers
Classifier: Topic :: Software Development
Classifier: License :: OSI Approved :: MIT License
Classifier: Operating System :: OS Independent
Classifier: Programming Language :: Python :: 3.10
Classifier: Programming Language :: Python :: 3.11
Classifier: Programming Language :: Python :: 3.12
Classifier: Programming Language :: Python :: 3.13
Classifier: Programming Language :: Python :: 3.14
Classifier: Programming Language :: Python :: 3 :: Only
License-File: LICENSE
Requires-Dist: scipy>=1.4.1,<2.0.0
Requires-Dist: scikit_learn>=1.0.0,<2.0.0
Requires-Dist: numpy>=1.26.4,<3.0.0
Project-URL: documentation, https://github.com/nicoloverardo/matrix_regression
Project-URL: homepage, https://github.com/nicoloverardo/matrix_regression
Project-URL: repository, https://github.com/nicoloverardo/matrix_regression
